{
    "HiGHS_CMD": {
        "time": 303,
        "optimal": true,
        "obj": 932,
        "sol": [
            [
                89
            ],
            [
                83
            ],
            [
                88
            ],
            [
                46
            ],
            [
                76
            ],
            [
                69
            ],
            [
                91
            ],
            [
                71
            ],
            [
                94
            ],
            [
                87
            ],
            [
                73
            ],
            [
                90
            ],
            [
                80
            ],
            [
                10
            ],
            [
                78
            ],
            [
                60
            ],
            [
                93
            ],
            [
                95
            ],
            [
                86
            ],
            [
                67
            ]
        ]
    }
}